nasbench301/__init__.py
nasbench301/api.py
nasbench301/configspace.json
nasbench301/example.py
nasbench301/model_downloader.py
nasbench301/representations.py
nasbench301/surrogate_models/__init__.py
nasbench301/surrogate_models/create_data_splits.py
nasbench301/surrogate_models/create_data_splits_ablation.py
nasbench301/surrogate_models/ensemble.py
nasbench301/surrogate_models/fit_model.py
nasbench301/surrogate_models/surrogate_model.py
nasbench301/surrogate_models/utils.py
nasbench301/surrogate_models/bananas/__init__.py
nasbench301/surrogate_models/bananas/bananas.py
nasbench301/surrogate_models/bananas/bananas_utils.py
nasbench301/surrogate_models/bananas/bananas_src/__init__.py
nasbench301/surrogate_models/bananas/bananas_src/acquisition_functions.py
nasbench301/surrogate_models/bananas/bananas_src/data.py
nasbench301/surrogate_models/bananas/bananas_src/generator.py
nasbench301/surrogate_models/bananas/bananas_src/meta_neural_net.py
nasbench301/surrogate_models/bananas/bananas_src/metann_runner.py
nasbench301/surrogate_models/bananas/bananas_src/nas_algorithms.py
nasbench301/surrogate_models/bananas/bananas_src/params.py
nasbench301/surrogate_models/bananas/bananas_src/run_experiments_sequential.py
nasbench301/surrogate_models/bananas/bananas_src/train_arch_runner.py
nasbench301/surrogate_models/bananas/bananas_src/bo/__init__.py
nasbench301/surrogate_models/bananas/bananas_src/bo/acq/__init__.py
nasbench301/surrogate_models/bananas/bananas_src/bo/acq/acqmap.py
nasbench301/surrogate_models/bananas/bananas_src/bo/acq/acqopt.py
nasbench301/surrogate_models/bananas/bananas_src/bo/acq/acquisition.py
nasbench301/surrogate_models/bananas/bananas_src/bo/bo/__init__.py
nasbench301/surrogate_models/bananas/bananas_src/bo/bo/probo.py
nasbench301/surrogate_models/bananas/bananas_src/bo/dom/__init__.py
nasbench301/surrogate_models/bananas/bananas_src/bo/dom/list.py
nasbench301/surrogate_models/bananas/bananas_src/bo/dom/real.py
nasbench301-0.3.dist-info/LICENSE
nasbench301-0.3.dist-info/METADATA
nasbench301-0.3.dist-info/WHEEL
nasbench301-0.3.dist-info/top_level.txt
nasbench301-0.3.dist-info/RECORD
