Metadata-Version: 2.1
Name: nasbench301
Version: 0.3
Summary: A surrogate benchmark for neural architecture search
Home-page: https://github.com/automl/nasbench301
Author: AutoML Freiburg
Author-email: zimmerl@informatik.uni-freiburg.de
License: 3-clause BSD
Keywords: machine learningoptimization tuning neural architecture deep learning
Platform: Linux
Classifier: Development Status :: 3 - Alpha
Classifier: Topic :: Utilities
Classifier: Topic :: Scientific/Engineering
Classifier: Topic :: Scientific/Engineering :: Artificial Intelligence
Classifier: Programming Language :: Python :: 3
Classifier: License :: OSI Approved :: BSD License
Requires-Python: >=3
